llmtools/__init__.py
pyllmtools-0.0.2.dist-info/LICENSE
pyllmtools-0.0.2.dist-info/WHEEL
pyllmtools-0.0.2.dist-info/METADATA
pyllmtools-0.0.2.dist-info/RECORD
